libentry/__init__.py
libentry/api.py
libentry/argparse.py
libentry/dataclasses.py
libentry/executor.py
libentry/experiment.py
libentry/json.py
libentry/logging.py
libentry/resource.py
libentry/schema.py
libentry/test_api.py
libentry/utils.py
libentry/mcp/__init__.py
libentry/mcp/api.py
libentry/mcp/client.py
libentry/mcp/service.py
libentry/mcp/types.py
libentry/service/__init__.py
libentry/service/common.py
libentry/service/flask.py
libentry/service/list.py
libentry/service/running.py
libentry/service/start.py
libentry/service/stop.py
libentry-1.33.5.dist-info/LICENSE
libentry-1.33.5.dist-info/METADATA
libentry-1.33.5.dist-info/WHEEL
libentry-1.33.5.dist-info/entry_points.txt
libentry-1.33.5.dist-info/top_level.txt
libentry-1.33.5.dist-info/zip-safe
libentry-1.33.5.dist-info/RECORD
